{   
  "challenge": {
    "intro": {
      "daring": [
        {"time":0,"type":"sentence","start":7,"end":48,"value":"Let's begin the identity theft challenge.", "element":"narrate-section"},
        {"time":25,"type":"word","start":7,"end":12,"value":"Let's", "element":"narrate-section"},
        {"time":275,"type":"word","start":13,"end":18,"value":"begin", "element":"narrate-section"},
        {"time":587,"type":"word","start":19,"end":22,"value":"the", "element":"narrate-section"},
        {"time":700,"type":"word","start":23,"end":31,"value":"identity", "element":"narrate-section"},
        {"time":1200,"type":"word","start":32,"end":37,"value":"theft", "element":"narrate-section"},
        {"time":1500,"type":"word","start":38,"end":47,"value":"challenge", "element":"narrate-section"},
        {"time":2680,"type":"sentence","start":49,"end":91,"value":"It will take around 5 minutes to complete.", "element":"narrate-time"},
        {"time":2705,"type":"word","start":49,"end":51,"value":"It", "element":"narrate-time"},
        {"time":2805,"type":"word","start":52,"end":56,"value":"will", "element":"narrate-time"},
        {"time":2955,"type":"word","start":57,"end":61,"value":"take", "element":"narrate-time"},
        {"time":3242,"type":"word","start":62,"end":68,"value":"around", "element":"narrate-time"},
        {"time":3580,"type":"word","start":69,"end":70,"value":"5 min", "element":"narrate-time"},
        {"time":4192,"type":"word","start":79,"end":81,"value":"to", "element":"narrate-time"},
        {"time":4280,"type":"word","start":82,"end":90,"value":"complete", "element":"narrate-time"},
        {"time":4980,"type":"word","start":91,"end":113,"value":"<break time=\"1000ms\"/>", "element":"narrate-time"},
        {"time":6360,"type":"sentence","start":113,"end":159,"value":"Find out your Identity Theft Resilience Score!", "element":"narrate-1"},
        {"time":6385,"type":"word","start":113,"end":117,"value":"Find", "element":"narrate-1"},
        {"time":6735,"type":"word","start":118,"end":121,"value":"out", "element":"narrate-1"},
        {"time":6960,"type":"word","start":122,"end":126,"value":"your", "element":"narrate-1"},
        {"time":7122,"type":"word","start":127,"end":135,"value":"Identity", "element":"narrate-1"},
        {"time":7535,"type":"word","start":136,"end":141,"value":"Theft", "element":"narrate-1"},
        {"time":7822,"type":"word","start":142,"end":152,"value":"Resilience", "element":"narrate-1"},
        {"time":8335,"type":"word","start":153,"end":158,"value":"Score", "element":"narrate-1"},
        {"time":8910,"type":"word","start":159,"end":180,"value":"<break time=\"500ms\"/>", "element":"narrate-1"},
        {"time":9790,"type":"sentence","start":180,"end":234,"value":"DART HQ has gathered a variety of suspicious messages.", "element":"narrate-2"},
        {"time":9815,"type":"word","start":180,"end":184,"value":"DART", "element":"narrate-2"},
        {"time":10052,"type":"word","start":185,"end":187,"value":"HQ", "element":"narrate-2"},
        {"time":10615,"type":"word","start":188,"end":191,"value":"has", "element":"narrate-2"},
        {"time":10840,"type":"word","start":192,"end":200,"value":"gathered", "element":"narrate-2"},
        {"time":11202,"type":"word","start":201,"end":202,"value":"a", "element":"narrate-2"},
        {"time":11265,"type":"word","start":203,"end":210,"value":"variety", "element":"narrate-2"},
        {"time":11865,"type":"word","start":211,"end":213,"value":"of", "element":"narrate-2"},
        {"time":11977,"type":"word","start":214,"end":224,"value":"suspicious", "element":"narrate-2"},
        {"time":12577,"type":"word","start":225,"end":233,"value":"messages", "element":"narrate-2"},
        {"time":13757,"type":"sentence","start":235,"end":245,"value":"Your task?", "element":"narrate-2"},
        {"time":13782,"type":"word","start":235,"end":239,"value":"Your", "element":"narrate-2"},
        {"time":13920,"type":"word","start":240,"end":244,"value":"task", "element":"narrate-2"},
        {"time":14912,"type":"sentence","start":246,"end":303,"value":"Differentiate between what’s genuine and what's a scam.", "element":"narrate-2"},
        {"time":14937,"type":"word","start":246,"end":259,"value":"Differentiate", "element":"narrate-2"},
        {"time":15687,"type":"word","start":260,"end":267,"value":"between", "element":"narrate-2"},
        {"time":16087,"type":"word","start":268,"end":276,"value":"what’s", "element":"narrate-2"},
        {"time":16337,"type":"word","start":277,"end":284,"value":"genuine", "element":"narrate-2"},
        {"time":16837,"type":"word","start":285,"end":288,"value":"and", "element":"narrate-2"},
        {"time":17025,"type":"word","start":289,"end":295,"value":"what's", "element":"narrate-2"},
        {"time":17250,"type":"word","start":296,"end":297,"value":"a", "element":"narrate-2"},
        {"time":17300,"type":"word","start":298,"end":302,"value":"scam", "element":"narrate-2"},
        {"time":18280,"type":"sentence","start":304,"end":373,"value":"Take this to assess your current knowledge and earn your first badge!", "element":"narrate-3"},
        {"time":18305,"type":"word","start":304,"end":308,"value":"Take", "element":"narrate-3"},
        {"time":18567,"type":"word","start":309,"end":313,"value":"this", "element":"narrate-3"},
        {"time":18780,"type":"word","start":314,"end":316,"value":"to", "element":"narrate-3"},
        {"time":18917,"type":"word","start":317,"end":323,"value":"assess", "element":"narrate-3"},
        {"time":19255,"type":"word","start":324,"end":328,"value":"your", "element":"narrate-3"},
        {"time":19342,"type":"word","start":329,"end":336,"value":"current", "element":"narrate-3"},
        {"time":19680,"type":"word","start":337,"end":346,"value":"knowledge", "element":"narrate-3"},
        {"time":20167,"type":"word","start":347,"end":350,"value":"and", "element":"narrate-3"},
        {"time":20280,"type":"word","start":351,"end":355,"value":"earn", "element":"narrate-3"},
        {"time":20442,"type":"word","start":356,"end":360,"value":"your", "element":"narrate-3"},
        {"time":20542,"type":"word","start":361,"end":366,"value":"first", "element":"narrate-3"},
        {"time":20905,"type":"word","start":367,"end":372,"value":"badge", "element":"narrate-3"},
        {"time":21492,"type":"word","start":373,"end":394,"value":"<break time=\"500ms\"\/>", "element":"narrate-4"},
        {"time":22372,"type":"sentence","start":394,"end":447,"value":"Click the 'Next' button below to start the challenge.", "element":"narrate-4"},
        {"time":22397,"type":"word","start":394,"end":399,"value":"Click", "element":"narrate-4"},
        {"time":22635,"type":"word","start":400,"end":403,"value":"the", "element":"narrate-4"},
        {"time":22722,"type":"word","start":404,"end":410,"value":"'Next'", "element":"narrate-4"},
        {"time":23047,"type":"word","start":411,"end":417,"value":"button", "element":"narrate-4"},
        {"time":23322,"type":"word","start":418,"end":423,"value":"below", "element":"narrate-4"},
        {"time":23685,"type":"word","start":424,"end":426,"value":"to", "element":"narrate-4"},
        {"time":23822,"type":"word","start":427,"end":432,"value":"start", "element":"narrate-4"},
        {"time":24147,"type":"word","start":433,"end":436,"value":"the", "element":"narrate-4"},
        {"time":24222,"type":"word","start":437,"end":446,"value":"challenge", "element":"narrate-4"}
      ],
      "intrepid": [
        {"time":0,"type":"sentence","start":7,"end":48,"value":"Let's begin the identity theft challenge.", "element":"narrate"},
        {"time":137,"type":"word","start":7,"end":12,"value":"Let's", "element":"narrate"},
        {"time":375,"type":"word","start":13,"end":18,"value":"begin", "element":"narrate"},
        {"time":687,"type":"word","start":19,"end":22,"value":"the", "element":"narrate"},
        {"time":837,"type":"word","start":23,"end":31,"value":"identity", "element":"narrate"},
        {"time":1437,"type":"word","start":32,"end":37,"value":"theft", "element":"narrate"},
        {"time":1750,"type":"word","start":38,"end":47,"value":"challenge", "element":"narrate"},
        {"time":2705,"type":"sentence","start":49,"end":91,"value":"It will take around 5 minutes to complete.", "element":"narrate"},
        {"time":2842,"type":"word","start":49,"end":51,"value":"It", "element":"narrate"},
        {"time":2955,"type":"word","start":52,"end":56,"value":"will", "element":"narrate"},
        {"time":3080,"type":"word","start":57,"end":61,"value":"take", "element":"narrate"},
        {"time":3392,"type":"word","start":62,"end":68,"value":"around", "element":"narrate"},
        {"time":3705,"type":"word","start":69,"end":70,"value":"5", "element":"narrate"},
        {"time":4017,"type":"word","start":71,"end":78,"value":"minutes", "element":"narrate"},
        {"time":4330,"type":"word","start":79,"end":81,"value":"to", "element":"narrate"},
        {"time":4467,"type":"word","start":82,"end":90,"value":"complete", "element":"narrate"},
        {"time":5105,"type":"word","start":91,"end":113,"value":"<break time=\"1000ms\"/>", "element":"narrate"},
        {"time":6485,"type":"sentence","start":113,"end":159,"value":"Find out your Identity Theft Resilience Score!", "element":"narrate"},
        {"time":6672,"type":"word","start":113,"end":117,"value":"Find", "element":"narrate"},
        {"time":6985,"type":"word","start":118,"end":121,"value":"out", "element":"narrate"},
        {"element":"narrate", "time":7110,"type":"word","start":122,"end":126,"value":"your"},
        {"element":"narrate", "time":7322,"type":"word","start":127,"end":135,"value":"Identity"},
        {"element":"narrate", "time":7922,"type":"word","start":136,"end":141,"value":"Theft"},
        {"element":"narrate", "time":8185,"type":"word","start":142,"end":152,"value":"Resilience"},
        {"element":"narrate", "time":8747,"type":"word","start":153,"end":158,"value":"Score"},
        {"element":"narrate", "time":9272,"type":"word","start":159,"end":180,"value":"<break time=\"500ms\"/>"},
        {"element":"narrate", "time":10152,"type":"sentence","start":180,"end":234,"value":"DART HQ has gathered a variety of suspicious messages."},
        {"element":"narrate", "time":10340,"type":"word","start":180,"end":184,"value":"DART"},
        {"element":"narrate", "time":10715,"type":"word","start":185,"end":187,"value":"HQ"},
        {"element":"narrate", "time":11152,"type":"word","start":188,"end":191,"value":"has"},
        {"element":"narrate", "time":11352,"type":"word","start":192,"end":200,"value":"gathered"},
        {"element":"narrate", "time":11715,"type":"word","start":201,"end":202,"value":"a"},
        {"element":"narrate", "time":11777,"type":"word","start":203,"end":210,"value":"variety"},
        {"element":"narrate", "time":12390,"type":"word","start":211,"end":213,"value":"of"},
        {"element":"narrate", "time":12477,"type":"word","start":214,"end":224,"value":"suspicious"},
        {"element":"narrate", "time":13102,"type":"word","start":225,"end":233,"value":"messages"},
        {"element":"narrate", "time":14207,"type":"sentence","start":235,"end":245,"value":"Your task?", "element":"narrate"},
        {"element":"narrate", "time":14395,"type":"word","start":235,"end":239,"value":"Your"},
        {"element":"narrate", "time":14520,"type":"word","start":240,"end":244,"value":"task"},
        {"element":"narrate", "time":15575,"type":"sentence","start":246,"end":303,"value":"Differentiate between what’s genuine and what's a scam.", "element":"narrate"},
        {"element":"narrate", "time":15762,"type":"word","start":246,"end":259,"value":"Differentiate"},
        {"element":"narrate", "time":16412,"type":"word","start":260,"end":267,"value":"between"},
        {"element":"narrate", "time":16825,"type":"word","start":268,"end":276,"value":"what’s"},
        {"element":"narrate", "time":17137,"type":"word","start":277,"end":284,"value":"genuine"},
        {"element":"narrate", "time":17600,"type":"word","start":285,"end":288,"value":"and"},
        {"element":"narrate", "time":17712,"type":"word","start":289,"end":295,"value":"what's"},
        {"element":"narrate", "time":17950,"type":"word","start":296,"end":297,"value":"a"},
        {"element":"narrate", "time":18037,"type":"word","start":298,"end":302,"value":"scam"},
        {"element":"narrate", "time":19005,"type":"sentence","start":304,"end":373,"value":"Take this to assess your current knowledge and earn your first badge!"},
        {"element":"narrate", "time":19192,"type":"word","start":304,"end":308,"value":"Take"},
        {"element":"narrate", "time":19380,"type":"word","start":309,"end":313,"value":"this"},
        {"element":"narrate", "time":19567,"type":"word","start":314,"end":316,"value":"to"},
        {"element":"narrate", "time":19717,"type":"word","start":317,"end":323,"value":"assess"},
        {"element":"narrate", "time":20067,"type":"word","start":324,"end":328,"value":"your"},
        {"element":"narrate", "time":20255,"type":"word","start":329,"end":336,"value":"current"},
        {"element":"narrate", "time":20630,"type":"word","start":337,"end":346,"value":"knowledge"},
        {"element":"narrate", "time":21042,"type":"word","start":347,"end":350,"value":"and"},
        {"element":"narrate", "time":21192,"type":"word","start":351,"end":355,"value":"earn"},
        {"element":"narrate", "time":21317,"type":"word","start":356,"end":360,"value":"your"},
        {"element":"narrate", "time":21467,"type":"word","start":361,"end":366,"value":"first"},
        {"element":"narrate", "time":21755,"type":"word","start":367,"end":372,"value":"badge"},
        {"element":"narrate", "time":22317,"type":"word","start":373,"end":394,"value":"<break time=\"500ms\"/>"},
        {"element":"narrate", "time":23197,"type":"sentence","start":394,"end":447,"value":"Click the 'Next' button below to start the challenge."},
        {"element":"narrate", "time":23335,"type":"word","start":394,"end":399,"value":"Click"},
        {"element":"narrate", "time":23572,"type":"word","start":400,"end":403,"value":"the"},
        {"element":"narrate", "time":23697,"type":"word","start":404,"end":410,"value":"'Next'"},
        {"element":"narrate", "time":24010,"type":"word","start":411,"end":417,"value":"button"},
        {"element":"narrate", "time":24260,"type":"word","start":418,"end":423,"value":"below"},
        {"element":"narrate", "time":24572,"type":"word","start":424,"end":426,"value":"to"},
        {"element":"narrate", "time":24760,"type":"word","start":427,"end":432,"value":"start"},
        {"element":"narrate", "time":25035,"type":"word","start":433,"end":436,"value":"the"},
        {"element":"narrate", "time":25135,"type":"word","start":437,"end":446,"value":"challenge"}                
      ],
      "valiant": [
        {"time":0,"type":"sentence","start":7,"end":48,"value":"Let's begin the identity theft challenge.", "element":"narrate"},
        {"time":150,"type":"word","start":7,"end":12,"value":"Let's", "element":"narrate"},
        {"time":305,"type":"word","start":13,"end":18,"value":"begin", "element":"narrate"},
        {"time":500,"type":"word","start":19,"end":22,"value":"the", "element":"narrate"},
        {"time":620,"type":"word","start":23,"end":31,"value":"identity", "element":"narrate"},
        {"time":945,"type":"word","start":32,"end":37,"value":"theft", "element":"narrate"},
        {"time":1175,"type":"word","start":38,"end":47,"value":"challenge", "element":"narrate"},
        {"time":1650,"type":"sentence","start":49,"end":91,"value":"It will take around 5 minutes to complete.", "element":"narrate"},
        {"time":1700,"type":"word","start":49,"end":51,"value":"It", "element":"narrate"},
        {"time":1785,"type":"word","start":52,"end":56,"value":"will", "element":"narrate"},
        {"time":1870,"type":"word","start":57,"end":61,"value":"take", "element":"narrate"},
        {"time":2050,"type":"word","start":62,"end":68,"value":"around", "element":"narrate"},
        {"time":2245,"type":"word","start":69,"end":70,"value":"5", "element":"narrate"},
        {"time":2415,"type":"word","start":71,"end":78,"value":"minutes", "element":"narrate"},
        {"time":2595,"type":"word","start":79,"end":81,"value":"to", "element":"narrate"},
        {"time":2670,"type":"word","start":82,"end":90,"value":"complete", "element":"narrate"},
        {"time":3030,"type":"word","start":91,"end":113,"value":"<break time=\"1000ms\"/>", "element":"narrate"},
        {"time":3820,"type":"sentence","start":113,"end":159,"value":"Find out your Identity Theft Resilience Score!", "element":"narrate"},
        {"time":3895,"type":"word","start":113,"end":117,"value":"Find", "element":"narrate"},
        {"time":4055,"type":"word","start":118,"end":121,"value":"out", "element":"narrate"},
        {"element":"narrate", "time":4210,"type":"word","start":122,"end":126,"value":"your"},
        {"element":"narrate", "time":4395,"type":"word","start":127,"end":135,"value":"Identity"},
        {"element":"narrate", "time":4765,"type":"word","start":136,"end":141,"value":"Theft"},
        {"element":"narrate", "time":5010,"type":"word","start":142,"end":152,"value":"Resilience"},
        {"element":"narrate", "time":5360,"type":"word","start":153,"end":158,"value":"Score"},
        {"element":"narrate", "time":5805,"type":"word","start":159,"end":180,"value":"<break time=\"500ms\"/>"},
        {"element":"narrate", "time":6405,"type":"sentence","start":180,"end":234,"value":"DART HQ has gathered a variety of suspicious messages."},
        {"element":"narrate", "time":6550,"type":"word","start":180,"end":184,"value":"DART"},
        {"element":"narrate", "time":6840,"type":"word","start":185,"end":187,"value":"HQ"},
        {"element":"narrate", "time":7205,"type":"word","start":188,"end":191,"value":"has"},
        {"element":"narrate", "time":7460,"type":"word","start":192,"end":200,"value":"gathered"},
        {"element":"narrate", "time":7760,"type":"word","start":201,"end":202,"value":"a"},
        {"element":"narrate", "time":7880,"type":"word","start":203,"end":210,"value":"variety"},
        {"element":"narrate", "time":8400,"type":"word","start":211,"end":213,"value":"of"},
        {"element":"narrate", "time":8520,"type":"word","start":214,"end":224,"value":"suspicious"},
        {"element":"narrate", "time":9050,"type":"word","start":225,"end":233,"value":"messages"},
        {"element":"narrate", "time":10100,"type":"sentence","start":235,"end":245,"value":"Your task?", "element":"narrate"},
        {"element":"narrate", "time":10205,"type":"word","start":235,"end":239,"value":"Your"},
        {"element":"narrate", "time":10430,"type":"word","start":240,"end":244,"value":"task"},
        {"element":"narrate", "time":11525,"type":"sentence","start":246,"end":303,"value":"Differentiate between what’s genuine and what's a scam.", "element":"narrate"},
        {"element":"narrate", "time":11655,"type":"word","start":246,"end":259,"value":"Differentiate"},
        {"element":"narrate", "time":12165,"type":"word","start":260,"end":267,"value":"between"},
        {"element":"narrate", "time":14675,"type":"word","start":268,"end":276,"value":"what’s"},
        {"element":"narrate", "time":14900,"type":"word","start":277,"end":284,"value":"genuine"},
        {"element":"narrate", "time":15300,"type":"word","start":285,"end":288,"value":"and"},
        {"element":"narrate", "time":15425,"type":"word","start":289,"end":295,"value":"what's"},
        {"element":"narrate", "time":15600,"type":"word","start":296,"end":297,"value":"a"},
        {"element":"narrate", "time":15637,"type":"word","start":298,"end":302,"value":"scam"},
        {"element":"narrate", "time":16592,"type":"sentence","start":304,"end":373,"value":"Take this to assess your current knowledge and earn your first badge!"},
        {"element":"narrate", "time":16617,"type":"word","start":304,"end":308,"value":"Take"},
        {"element":"narrate", "time":16830,"type":"word","start":309,"end":313,"value":"this"},
        {"element":"narrate", "time":17042,"type":"word","start":314,"end":316,"value":"to"},
        {"element":"narrate", "time":17167,"type":"word","start":317,"end":323,"value":"assess"},
        {"element":"narrate", "time":17492,"type":"word","start":324,"end":328,"value":"your"},
        {"element":"narrate", "time":17580,"type":"word","start":329,"end":336,"value":"current"},
        {"element":"narrate", "time":17930,"type":"word","start":337,"end":346,"value":"knowledge"},
        {"element":"narrate", "time":18342,"type":"word","start":347,"end":350,"value":"and"},
        {"element":"narrate", "time":18455,"type":"word","start":351,"end":355,"value":"earn"},
        {"element":"narrate", "time":18630,"type":"word","start":356,"end":360,"value":"your"},
        {"element":"narrate", "time":18730,"type":"word","start":361,"end":366,"value":"first"},
        {"element":"narrate", "time":19042,"type":"word","start":367,"end":372,"value":"badge"},
        {"element":"narrate", "time":19505,"type":"word","start":373,"end":394,"value":"<break time=\"500ms\"/>"},
        {"element":"narrate", "time":20385,"type":"sentence","start":394,"end":447,"value":"Click the 'Next' button below to start the challenge."},
        {"element":"narrate", "time":20410,"type":"word","start":394,"end":399,"value":"Click"},
        {"element":"narrate", "time":20622,"type":"word","start":400,"end":403,"value":"the"},
        {"element":"narrate", "time":20722,"type":"word","start":404,"end":410,"value":"'Next'"},
        {"element":"narrate", "time":20985,"type":"word","start":411,"end":417,"value":"button"},
        {"element":"narrate", "time":21272,"type":"word","start":418,"end":423,"value":"below"},
        {"element":"narrate", "time":21585,"type":"word","start":424,"end":426,"value":"to"},
        {"element":"narrate", "time":21647,"type":"word","start":427,"end":432,"value":"start"},
        {"element":"narrate", "time":21935,"type":"word","start":433,"end":436,"value":"the"},
        {"element":"narrate", "time":22010,"type":"word","start":437,"end":446,"value":"challenge"}
      ]
    }
  }
}
