{"_id":{"$oid":"59fc8401449b71fe7636ec9b"},"actor":{"$oid":"59fc83331fc54c9d4ce03506"},"post_id":1,"picture":"real_6.jpg","module":"digital_literacy","likes":1,"lowread":18,"highread":179,"time":-7200000}
{"_id":{"$oid":"59fc8401449b71fe7636ec9c"},"actor":{"$oid":"59fc83331fc54c9d4ce0350c"},"post_id":2,"picture":"six flags.jpeg","module":"digital_literacy","likes":1,"lowread":7,"highread":157,"time":-180000}
{"_id":{"$oid":"59fc8401449b71fe7636ec9d"},"actor":{"$oid":"59fc83331fc54c9d4ce03542"},"post_id":3,"picture":"clickbait_1.jpg","module":"digital_literacy","likes":1,"lowread":7,"highread":196,"time":-360000}
{"_id":{"$oid":"59fc8401449b71fe7636ec9e"},"actor":{"$oid":"59fc83331fc54c9d4ce03521"},"post_id":4,"picture":"flops1.jpeg","module":"digital_literacy","likes":2,"lowread":6,"highread":154,"time":-540000}
{"_id":{"$oid":"59fc8401449b71fe7636ec9f"},"actor":{"$oid":"59fc83331fc54c9d4ce0350c"},"post_id":5,"picture":"dog.JPG","module":"digital_literacy","likes":2,"lowread":13,"highread":153,"time":-720000}
{"_id":{"$oid":"59fc8401449b71fe7636eca0"},"actor":{"$oid":"59fc83331fc54c9d4ce0350d"},"post_id":6,"picture":"anime.png","module":"digital_literacy","likes":2,"lowread":11,"highread":202,"time":-900000}
{"_id":{"$oid":"59fc8401449b71fe7636eca1"},"actor":{"$oid":"59fc83331fc54c9d4ce0351a"},"post_id":7,"picture":"real_1.jpg","module":"digital_literacy","likes":2,"lowread":11,"highread":188,"time":-1080000}
{"_id":{"$oid":"59fc8401449b71fe7636eca2"},"actor":{"$oid":"59fc83331fc54c9d4ce03503"},"post_id":9,"picture":"prank.jpg","module":"digital_literacy","likes":1,"lowread":10,"highread":178,"time":-1440000}
{"_id":{"$oid":"59fc8401449b71fe7636eca3"},"actor":{"$oid":"59fc83331fc54c9d4ce03520"},"post_id":10,"picture":"clickbait_2.jpg","module":"digital_literacy","likes":3,"lowread":15,"highread":163,"time":-1620000}
{"_id":{"$oid":"59fc8401449b71fe7636eca4"},"actor":{"$oid":"59fc83331fc54c9d4ce03520"},"post_id":11,"picture":"girl2.jpg","module":"digital_literacy","likes":2,"lowread":6,"highread":156,"time":-1800000}
{"_id":{"$oid":"59fc8401449b71fe7636eca5"},"actor":{"$oid":"59fc83331fc54c9d4ce03514"},"post_id":12,"picture":"driving.jpg","module":"digital_literacy","likes":4,"lowread":18,"highread":153,"time":-1980000}
{"_id":{"$oid":"59fc8401449b71fe7636eca6"},"actor":{"$oid":"59fc83331fc54c9d4ce03536"},"post_id":13,"picture":"makeup.jpg","module":"digital_literacy","likes":2,"lowread":7,"highread":168,"time":-2160000}
{"_id":{"$oid":"59fc8401449b71fe7636eca7"},"actor":{"$oid":"59fc83331fc54c9d4ce03502"},"post_id":14,"picture":"real_2.jpg","module":"digital_literacy","likes":2,"lowread":7,"highread":160,"time":-2340000}
{"_id":{"$oid":"59fc8401449b71fe7636eca8"},"actor":{"$oid":"59fc83331fc54c9d4ce0352d"},"post_id":15,"picture":"tea.jpg","module":"digital_literacy","likes":2,"lowread":8,"highread":175,"time":-2520000}
{"_id":{"$oid":"59fc8401449b71fe7636eca9"},"actor":{"$oid":"59fc83331fc54c9d4ce03527"},"post_id":16,"picture":"rosegold.png","module":"digital_literacy","likes":1,"lowread":19,"highread":192,"time":-2700000}
{"_id":{"$oid":"59fc8401449b71fe7636ecaa"},"actor":{"$oid":"59fc83331fc54c9d4ce03525"},"post_id":17,"picture":"cheer.jpg","module":"digital_literacy","likes":1,"lowread":18,"highread":156,"time":-2880000}
{"_id":{"$oid":"59fc8401449b71fe7636ecab"},"actor":{"$oid":"59fc83331fc54c9d4ce03540"},"post_id":18,"picture":"clickbait_3.jpg","module":"digital_literacy","likes":2,"lowread":8,"highread":164,"time":-3060000}
{"_id":{"$oid":"59fc8401449b71fe7636ecac"},"actor":{"$oid":"59fc83331fc54c9d4ce03502"},"post_id":19,"picture":"boyspic.jpg","module":"digital_literacy","likes":5,"lowread":7,"highread":199,"time":-3240000}
{"_id":{"$oid":"59fc8401449b71fe7636ecad"},"actor":{"$oid":"59fc83331fc54c9d4ce03539"},"post_id":20,"picture":"dance.jpg","module":"digital_literacy","likes":4,"lowread":7,"highread":157,"time":-3420000}
{"_id":{"$oid":"59fc8401449b71fe7636ecae"},"actor":{"$oid":"59fc83331fc54c9d4ce03504"},"post_id":21,"picture":"real_3.jpg","module":"digital_literacy","likes":5,"lowread":18,"highread":154,"time":-3600000}
{"_id":{"$oid":"59fc8401449b71fe7636ecaf"},"actor":{"$oid":"59fc83331fc54c9d4ce0350b"},"post_id":22,"picture":"post83.jpg","module":"digital_literacy","likes":6,"lowread":6,"highread":150,"time":3420000}
{"_id":{"$oid":"59fc8401449b71fe7636ecb0"},"actor":{"$oid":"59fc83331fc54c9d4ce03526"},"post_id":24,"picture":"football1.jpg","module":"digital_literacy","likes":6,"lowread":6,"highread":200,"time":3060000}
{"_id":{"$oid":"59fc8401449b71fe7636ecb1"},"actor":{"$oid":"59fc83331fc54c9d4ce0351e"},"post_id":25,"picture":"clickbait_4.jpg","module":"digital_literacy","likes":1,"lowread":11,"highread":180,"time":2880000}
{"_id":{"$oid":"59fc8401449b71fe7636ecb2"},"actor":{"$oid":"59fc83331fc54c9d4ce03525"},"post_id":26,"picture":"cheer.jpg","module":"digital_literacy","likes":1,"lowread":11,"highread":151,"time":2700000}
{"_id":{"$oid":"59fc8401449b71fe7636ecb3"},"actor":{"$oid":"59fc83331fc54c9d4ce03515"},"post_id":27,"picture":"Puppy.jpg","module":"digital_literacy","likes":4,"lowread":11,"highread":145,"time":2520000}
{"_id":{"$oid":"59fc8401449b71fe7636ecb4"},"actor":{"$oid":"59fc83331fc54c9d4ce03501"},"post_id":28,"picture":"real_4.jpg","module":"digital_literacy","likes":4,"lowread":14,"highread":187,"time":2340000}
{"_id":{"$oid":"59fc8401449b71fe7636ecb5"},"actor":{"$oid":"59fc83331fc54c9d4ce0352a"},"post_id":29,"picture":"missingsummer.jpg","module":"digital_literacy","likes":4,"lowread":9,"highread":202,"time":2160000}
{"_id":{"$oid":"59fc8401449b71fe7636ecb6"},"actor":{"$oid":"59fc83331fc54c9d4ce03543"},"post_id":30,"picture":"post36.jpg","module":"digital_literacy","likes":6,"lowread":17,"highread":175,"time":1980000}
{"_id":{"$oid":"59fc8401449b71fe7636ecb7"},"actor":{"$oid":"59fc83331fc54c9d4ce0353d"},"post_id":31,"picture":"clickbait_5.jpg","module":"digital_literacy","likes":3,"lowread":19,"highread":199,"time":1800000}
{"_id":{"$oid":"59fc8401449b71fe7636ecb8"},"actor":{"$oid":"59fc83331fc54c9d4ce03513"},"post_id":32,"picture":"budgie.jpg","module":"digital_literacy","likes":2,"lowread":12,"highread":191,"time":1620000}
{"_id":{"$oid":"59fc8401449b71fe7636ecb9"},"actor":{"$oid":"59fc83331fc54c9d4ce0352c"},"post_id":33,"picture":"playing_minecraft.jpg","module":"digital_literacy","likes":1,"lowread":11,"highread":148,"time":1440000}
{"_id":{"$oid":"59fc8401449b71fe7636ecba"},"actor":{"$oid":"59fc83331fc54c9d4ce03520"},"post_id":34,"picture":"Roadtrip.jpg","module":"digital_literacy","likes":3,"lowread":18,"highread":157,"time":1260000}
{"_id":{"$oid":"59fc8401449b71fe7636ecbb"},"actor":{"$oid":"59fc83331fc54c9d4ce03510"},"post_id":35,"picture":"real_5.jpg","module":"digital_literacy","likes":1,"lowread":15,"highread":147,"time":1080000}
{"_id":{"$oid":"59fc8401449b71fe7636ecbc"},"actor":{"$oid":"59fc83331fc54c9d4ce0350a"},"post_id":36,"picture":"u3p1.jpg","module":"digital_literacy","likes":3,"lowread":8,"highread":189,"time":900000}
{"_id":{"$oid":"59fc8401449b71fe7636ecbd"},"actor":{"$oid":"59fc83331fc54c9d4ce03532"},"post_id":37,"picture":"ilovenature.jpg","module":"digital_literacy","likes":4,"lowread":9,"highread":146,"time":720000}
{"_id":{"$oid":"59fc8401449b71fe7636ecbe"},"actor":{"$oid":"59fc83331fc54c9d4ce0353d"},"post_id":38,"picture":"yankee.jpg","module":"digital_literacy","likes":1,"lowread":7,"highread":189,"time":540000}
{"_id":{"$oid":"59fc8401449b71fe7636ecbf"},"actor":{"$oid":"59fc83331fc54c9d4ce03513"},"post_id":39,"picture":"clickbait_6.jpg","module":"digital_literacy","likes":3,"lowread":6,"highread":199,"time":360000}
{"_id":{"$oid":"59fc8401449b71fe7636ecc0"},"actor":{"$oid":"59fc83331fc54c9d4ce03525"},"post_id":40,"picture":"u5p2.jpg","module":"digital_literacy","likes":4,"lowread":6,"highread":179,"time":180000}
{"_id":{"$oid":"59fc8401449b71fe7636ecc1"},"actor":{"$oid":"59fc83331fc54c9d4ce03511"},"post_id":41,"picture":"Sunset-Love-Best-Friend.jpg","module":"cyberbullying","likes":2,"lowread":6,"highread":186,"time":-7200000}
{"_id":{"$oid":"59fc8401449b71fe7636ecc2"},"actor":{"$oid":"59fc83331fc54c9d4ce03509"},"post_id":42,"picture":"cutesiblings.jpg","module":"cyberbullying","likes":2,"lowread":7,"highread":195,"time":-180000}
{"_id":{"$oid":"59fc8401449b71fe7636ecc3"},"actor":{"$oid":"59fc83331fc54c9d4ce03505"},"post_id":43,"picture":"calculator.jpg","module":"cyberbullying","likes":1,"lowread":11,"highread":169,"time":-360000}
{"_id":{"$oid":"59fc8401449b71fe7636ecc4"},"actor":{"$oid":"59fc83331fc54c9d4ce03519"},"post_id":44,"picture":"eyeroll.jpg","module":"cyberbullying","likes":2,"lowread":17,"highread":195,"time":-540000}
{"_id":{"$oid":"59fc8401449b71fe7636ecc5"},"actor":{"$oid":"59fc83331fc54c9d4ce03518"},"post_id":45,"picture":"ewww.jpg","module":"cyberbullying","likes":2,"lowread":17,"highread":169,"time":-720000}
{"_id":{"$oid":"59fc8401449b71fe7636ecc6"},"actor":{"$oid":"59fc83331fc54c9d4ce03529"},"post_id":46,"picture":"party.jpg","module":"cyberbullying","likes":4,"lowread":11,"highread":152,"time":-900000}
{"_id":{"$oid":"59fc8401449b71fe7636ecc7"},"actor":{"$oid":"59fc83331fc54c9d4ce0350e"},"post_id":47,"picture":"heartbroken.jpg","module":"cyberbullying","likes":1,"lowread":17,"highread":154,"time":-1080000}
{"_id":{"$oid":"59fc8401449b71fe7636ecc8"},"actor":{"$oid":"59fc83331fc54c9d4ce0352d"},"post_id":48,"picture":"best_friends.jpg","module":"cyberbullying","likes":2,"lowread":19,"highread":148,"time":-1260000}
{"_id":{"$oid":"59fc8401449b71fe7636ecc9"},"actor":{"$oid":"59fc83331fc54c9d4ce03501"},"post_id":49,"picture":"winter_break.jpg","module":"cyberbullying","likes":4,"lowread":9,"highread":172,"time":-1440000}
{"_id":{"$oid":"59fc8401449b71fe7636ecca"},"actor":{"$oid":"59fc83331fc54c9d4ce0350b"},"post_id":50,"picture":"silly pic.jpeg","module":"cyberbullying","likes":6,"lowread":13,"highread":146,"time":-1620000}
{"_id":{"$oid":"59fc8401449b71fe7636eccb"},"actor":{"$oid":"59fc83331fc54c9d4ce03515"},"post_id":51,"picture":"emoji1.jpg","module":"cyberbullying","likes":6,"lowread":13,"highread":159,"time":-1800000}
{"_id":{"$oid":"59fc8401449b71fe7636eccc"},"actor":{"$oid":"59fc83331fc54c9d4ce0352e"},"post_id":52,"picture":"emoji2.png","module":"cyberbullying","likes":1,"lowread":8,"highread":169,"time":-1980000}
{"_id":{"$oid":"59fc8401449b71fe7636eccd"},"actor":{"$oid":"59fc83331fc54c9d4ce03537"},"post_id":53,"picture":"bus.jpg","module":"cyberbullying","likes":3,"lowread":16,"highread":191,"time":-2160000}
{"_id":{"$oid":"59fc8401449b71fe7636ecce"},"actor":{"$oid":"59fc83331fc54c9d4ce03541"},"post_id":54,"picture":"beach.jpg","module":"cyberbullying","likes":1,"lowread":13,"highread":193,"time":-2340000}
{"_id":{"$oid":"59fc8401449b71fe7636eccf"},"actor":{"$oid":"59fc83331fc54c9d4ce03518"},"post_id":55,"picture":"group_photo.jpg","module":"cyberbullying","likes":6,"lowread":6,"highread":145,"time":-2520000}
{"_id":{"$oid":"59fc8401449b71fe7636ecd0"},"actor":{"$oid":"59fc83331fc54c9d4ce0352b"},"post_id":56,"picture":"birthdaywishes.jpg","module":"cyberbullying","likes":1,"lowread":14,"highread":152,"time":-2700000}
{"_id":{"$oid":"59fc8401449b71fe7636ecd1"},"actor":{"$oid":"59fc83331fc54c9d4ce03501"},"post_id":57,"picture":"cute_dog.jpg","module":"cyberbullying","likes":1,"lowread":18,"highread":186,"time":-2880000}
{"_id":{"$oid":"59fc8401449b71fe7636ecd2"},"actor":{"$oid":"59fc83331fc54c9d4ce0350b"},"post_id":58,"picture":"girl_math.jpg","module":"cyberbullying","likes":5,"lowread":12,"highread":197,"time":-3060000}
{"_id":{"$oid":"59fc8401449b71fe7636ecd3"},"actor":{"$oid":"59fc83331fc54c9d4ce03511"},"post_id":59,"picture":"bad_cook.jpg","module":"cyberbullying","likes":4,"lowread":11,"highread":158,"time":-3240000}
{"_id":{"$oid":"59fc8401449b71fe7636ecd4"},"actor":{"$oid":"59fc83331fc54c9d4ce0350e"},"post_id":60,"picture":"movie.png","module":"cyberbullying","likes":3,"lowread":8,"highread":149,"time":-3420000}
{"_id":{"$oid":"59fc8401449b71fe7636ecd5"},"actor":{"$oid":"59fc83331fc54c9d4ce03509"},"post_id":61,"picture":"class_schedule.jpg","module":"cyberbullying","likes":2,"lowread":8,"highread":183,"time":-3600000}
{"_id":{"$oid":"59fc8401449b71fe7636ecd6"},"actor":{"$oid":"59fc83331fc54c9d4ce0350d"},"post_id":62,"picture":"birthday pic.jpeg","module":"cyberbullying","likes":1,"lowread":9,"highread":199,"time":3420000}
{"_id":{"$oid":"59fc8401449b71fe7636ecd7"},"actor":{"$oid":"59fc83331fc54c9d4ce0352d"},"post_id":63,"picture":"chrysanthemum_tea.JPG","module":"cyberbullying","likes":1,"lowread":17,"highread":153,"time":3240000}
{"_id":{"$oid":"59fc8401449b71fe7636ecd8"},"actor":{"$oid":"59fc83331fc54c9d4ce0352d"},"post_id":64,"picture":"harrypotter.jpg","module":"cyberbullying","likes":1,"lowread":6,"highread":196,"time":3060000}
{"_id":{"$oid":"59fc8401449b71fe7636ecd9"},"actor":{"$oid":"59fc83331fc54c9d4ce03514"},"post_id":65,"picture":"sadface.png","module":"cyberbullying","likes":4,"lowread":8,"highread":187,"time":2880000}
{"_id":{"$oid":"59fc8401449b71fe7636ecda"},"actor":{"$oid":"59fc83331fc54c9d4ce03506"},"post_id":66,"picture":"cool.png","module":"cyberbullying","likes":1,"lowread":18,"highread":169,"time":2700000}
{"_id":{"$oid":"59fc8401449b71fe7636ecdb"},"actor":{"$oid":"59fc83331fc54c9d4ce0353a"},"post_id":67,"picture":"tswift.jpg","module":"cyberbullying","likes":3,"lowread":7,"highread":152,"time":2520000}
{"_id":{"$oid":"59fc8401449b71fe7636ecdc"},"actor":{"$oid":"59fc83331fc54c9d4ce0353a"},"post_id":68,"picture":"bored.jpg","module":"cyberbullying","likes":2,"lowread":8,"highread":201,"time":2340000}
{"_id":{"$oid":"59fc8401449b71fe7636ecdd"},"actor":{"$oid":"59fc83331fc54c9d4ce03542"},"post_id":69,"picture":"questionmark.jpg","module":"cyberbullying","likes":3,"lowread":9,"highread":150,"time":2160000}
{"_id":{"$oid":"59fc8401449b71fe7636ecde"},"actor":{"$oid":"59fc83331fc54c9d4ce03520"},"post_id":70,"picture":"quote.jpeg","module":"cyberbullying","likes":1,"lowread":15,"highread":164,"time":1980000}
{"_id":{"$oid":"59fc8401449b71fe7636ecdf"},"actor":{"$oid":"59fc83331fc54c9d4ce0352e"},"post_id":71,"picture":"sunset.jpg","module":"cyberbullying","likes":3,"lowread":19,"highread":202,"time":1800000}
{"_id":{"$oid":"59fc8401449b71fe7636ece0"},"actor":{"$oid":"59fc83331fc54c9d4ce0351a"},"post_id":72,"picture":"christmas.jpg","module":"cyberbullying","likes":4,"lowread":18,"highread":190,"time":1620000}
{"_id":{"$oid":"59fc8401449b71fe7636ece1"},"actor":{"$oid":"59fc83331fc54c9d4ce0350b"},"post_id":73,"picture":"pickle.jpg","module":"cyberbullying","likes":6,"lowread":18,"highread":162,"time":1440000}
{"_id":{"$oid":"59fc8401449b71fe7636ece2"},"actor":{"$oid":"59fc83331fc54c9d4ce03539"},"post_id":74,"picture":"Demi_Lovato.jpg","module":"cyberbullying","likes":1,"lowread":18,"highread":177,"time":1260000}
{"_id":{"$oid":"59fc8401449b71fe7636ece3"},"actor":{"$oid":"59fc83331fc54c9d4ce0351f"},"post_id":75,"picture":"football.jpg","module":"cyberbullying","likes":2,"lowread":14,"highread":168,"time":1080000}
{"_id":{"$oid":"59fc8401449b71fe7636ece4"},"actor":{"$oid":"59fc83331fc54c9d4ce03533"},"post_id":77,"picture":"hotel room.jpg","module":"cyberbullying","likes":3,"lowread":16,"highread":189,"time":720000}
{"_id":{"$oid":"59fc8401449b71fe7636ece5"},"actor":{"$oid":"59fc83331fc54c9d4ce0353d"},"post_id":78,"picture":"yankee.jpg","module":"cyberbullying","likes":3,"lowread":8,"highread":164,"time":540000}
{"_id":{"$oid":"59fc8401449b71fe7636ece6"},"actor":{"$oid":"59fc83331fc54c9d4ce03525"},"post_id":79,"picture":"u5p2.jpg","module":"cyberbullying","likes":5,"lowread":11,"highread":152,"time":360000}
{"_id":{"$oid":"59fc8401449b71fe7636ece7"},"actor":{"$oid":"59fc83331fc54c9d4ce0351c"},"post_id":80,"picture":"basketballlife.jpeg","module":"cyberbullying","likes":1,"lowread":9,"highread":192,"time":180000}
{"_id":{"$oid":"59fc8401449b71fe7636ece8"},"actor":{"$oid":"59fc83331fc54c9d4ce0350a"},"post_id":81,"picture":"u3p2.jpeg","module":"presentation","likes":6,"lowread":11,"highread":179,"time":-7200000}
{"_id":{"$oid":"59fc8401449b71fe7636ece9"},"actor":{"$oid":"59fc83331fc54c9d4ce0351b"},"post_id":82,"picture":"u4p1.jpg","module":"presentation","likes":2,"lowread":13,"highread":200,"time":-180000}
{"_id":{"$oid":"59fc8401449b71fe7636ecea"},"actor":{"$oid":"59fc83331fc54c9d4ce03525"},"post_id":83,"picture":"u5p1.jpg","module":"presentation","likes":4,"lowread":11,"highread":175,"time":-360000}
{"_id":{"$oid":"59fc8401449b71fe7636eceb"},"actor":{"$oid":"59fc83331fc54c9d4ce03512"},"post_id":84,"picture":"u6p1.jpeg","module":"presentation","likes":6,"lowread":6,"highread":152,"time":-540000}
{"_id":{"$oid":"59fc8401449b71fe7636ecec"},"actor":{"$oid":"59fc83331fc54c9d4ce03536"},"post_id":85,"picture":"reciept.jpg","module":"presentation","likes":2,"lowread":7,"highread":183,"time":-720000}
{"_id":{"$oid":"59fc8401449b71fe7636eced"},"actor":{"$oid":"59fc83331fc54c9d4ce03502"},"post_id":86,"picture":"boyspic.jpg","module":"presentation","likes":4,"lowread":7,"highread":163,"time":-900000}
{"_id":{"$oid":"59fc8401449b71fe7636ecee"},"actor":{"$oid":"59fc83331fc54c9d4ce03528"},"post_id":87,"picture":"u7p1.jpg","module":"presentation","likes":1,"lowread":12,"highread":179,"time":-1080000}
{"_id":{"$oid":"59fc8401449b71fe7636ecef"},"actor":{"$oid":"59fc83331fc54c9d4ce03527"},"post_id":88,"picture":"orange_drawing.jpeg","module":"presentation","likes":5,"lowread":6,"highread":187,"time":-1260000}
{"_id":{"$oid":"59fc8401449b71fe7636ecf0"},"actor":{"$oid":"59fc83331fc54c9d4ce034fd"},"post_id":89,"picture":"egg_on_sidewalk.jpeg","module":"presentation","likes":2,"lowread":10,"highread":176,"time":-1620000}
{"_id":{"$oid":"59fc8401449b71fe7636ecf1"},"actor":{"$oid":"59fc83331fc54c9d4ce03540"},"post_id":90,"picture":"ballet.jpg","module":"presentation","likes":2,"lowread":12,"highread":148,"time":-1980000}
{"_id":{"$oid":"59fc8401449b71fe7636ecf2"},"actor":{"$oid":"59fc83331fc54c9d4ce03529"},"post_id":91,"picture":"starbucks.jpg","module":"presentation","likes":2,"lowread":17,"highread":163,"time":-2160000}
{"_id":{"$oid":"59fc8401449b71fe7636ecf3"},"actor":{"$oid":"59fc83331fc54c9d4ce03512"},"post_id":92,"picture":"u6p2.jpeg","module":"presentation","likes":3,"lowread":15,"highread":180,"time":-2340000}
{"_id":{"$oid":"59fc8401449b71fe7636ecf4"},"actor":{"$oid":"59fc83331fc54c9d4ce03515"},"post_id":93,"picture":"Puppy.jpg","module":"presentation","likes":3,"lowread":16,"highread":196,"time":-2520000}
{"_id":{"$oid":"59fc8401449b71fe7636ecf5"},"actor":{"$oid":"59fc83331fc54c9d4ce0352a"},"post_id":94,"picture":"missingsummer.jpg","module":"presentation","likes":1,"lowread":7,"highread":197,"time":-2700000}
{"_id":{"$oid":"59fc8401449b71fe7636ecf6"},"actor":{"$oid":"59fc83331fc54c9d4ce03543"},"post_id":95,"picture":"post36.jpg","module":"presentation","likes":3,"lowread":15,"highread":192,"time":-2880000}
{"_id":{"$oid":"59fc8401449b71fe7636ecf7"},"actor":{"$oid":"59fc83331fc54c9d4ce0350b"},"post_id":96,"picture":"card.jpg","module":"presentation","likes":5,"lowread":6,"highread":193,"time":-3060000}
{"_id":{"$oid":"59fc8401449b71fe7636ecf8"},"actor":{"$oid":"59fc83331fc54c9d4ce03541"},"post_id":97,"picture":"post37.jpg","module":"presentation","likes":4,"lowread":6,"highread":164,"time":-3240000}
{"_id":{"$oid":"59fc8401449b71fe7636ecf9"},"actor":{"$oid":"59fc83331fc54c9d4ce03533"},"post_id":98,"picture":"post38.jpg","module":"presentation","likes":3,"lowread":10,"highread":198,"time":-3420000}
{"_id":{"$oid":"59fc8401449b71fe7636ecfa"},"actor":{"$oid":"59fc83331fc54c9d4ce03526"},"post_id":99,"picture":"post39.jpg","module":"presentation","likes":1,"lowread":11,"highread":159,"time":-3600000}
{"_id":{"$oid":"59fc8401449b71fe7636ecfb"},"actor":{"$oid":"59fc83331fc54c9d4ce03520"},"post_id":100,"picture":"house.jpg","module":"presentation","likes":2,"lowread":14,"highread":193,"time":3420000}
{"_id":{"$oid":"59fc8401449b71fe7636ecfc"},"actor":{"$oid":"59fc83331fc54c9d4ce0351e"},"post_id":101,"picture":"post41.jpg","module":"presentation","likes":4,"lowread":19,"highread":158,"time":3240000}
{"_id":{"$oid":"59fc8401449b71fe7636ecfd"},"actor":{"$oid":"59fc83331fc54c9d4ce03504"},"post_id":102,"picture":"post42.jpg","module":"presentation","likes":3,"lowread":14,"highread":149,"time":3060000}
{"_id":{"$oid":"59fc8401449b71fe7636ecfe"},"actor":{"$oid":"59fc83331fc54c9d4ce03518"},"post_id":103,"picture":"post43.jpg","module":"presentation","likes":1,"lowread":13,"highread":200,"time":2880000}
{"_id":{"$oid":"59fc8401449b71fe7636ecff"},"actor":{"$oid":"59fc83331fc54c9d4ce0351d"},"post_id":104,"picture":"post44.jpg","module":"presentation","likes":3,"lowread":19,"highread":145,"time":2520000}
{"_id":{"$oid":"59fc8401449b71fe7636ed00"},"actor":{"$oid":"59fc83331fc54c9d4ce03542"},"post_id":105,"picture":"shoes.jpg","module":"presentation","likes":3,"lowread":6,"highread":174,"time":2340000}
{"_id":{"$oid":"59fc8401449b71fe7636ed01"},"actor":{"$oid":"59fc83331fc54c9d4ce0352b"},"post_id":106,"picture":"post45.jpg","module":"presentation","likes":1,"lowread":6,"highread":187,"time":2160000}
{"_id":{"$oid":"59fc8401449b71fe7636ed02"},"actor":{"$oid":"59fc83331fc54c9d4ce03508"},"post_id":107,"picture":"post50.jpg","module":"presentation","likes":3,"lowread":10,"highread":151,"time":1980000}
{"_id":{"$oid":"59fc8401449b71fe7636ed03"},"actor":{"$oid":"59fc83331fc54c9d4ce0352f"},"post_id":108,"picture":"post54.jpg","module":"presentation","likes":2,"lowread":8,"highread":176,"time":1800000}
{"_id":{"$oid":"59fc8401449b71fe7636ed04"},"actor":{"$oid":"59fc83331fc54c9d4ce0353d"},"post_id":110,"picture":"beach.jpg","module":"presentation","likes":1,"lowread":8,"highread":157,"time":1440000}
{"_id":{"$oid":"59fc8401449b71fe7636ed05"},"actor":{"$oid":"59fc83331fc54c9d4ce0352a"},"post_id":111,"picture":"texting.jpg","module":"presentation","likes":4,"lowread":16,"highread":155,"time":1260000}
{"_id":{"$oid":"59fc8401449b71fe7636ed06"},"actor":{"$oid":"59fc83331fc54c9d4ce03528"},"post_id":112,"picture":"u7p2.jpg","module":"presentation","likes":6,"lowread":19,"highread":154,"time":1080000}
{"_id":{"$oid":"59fc8401449b71fe7636ed07"},"actor":{"$oid":"59fc83331fc54c9d4ce03502"},"post_id":114,"picture":"movies.jpg","module":"presentation","likes":2,"lowread":14,"highread":159,"time":720000}
{"_id":{"$oid":"59fc8401449b71fe7636ed08"},"actor":{"$oid":"59fc83331fc54c9d4ce0351f"},"post_id":115,"picture":"friends.jpg","module":"presentation","likes":2,"lowread":8,"highread":192,"time":540000}
{"_id":{"$oid":"59fc8401449b71fe7636ed09"},"actor":{"$oid":"59fc83331fc54c9d4ce03513"},"post_id":116,"picture":"budgie.jpg","module":"presentation","likes":4,"lowread":6,"highread":180,"time":360000}
{"_id":{"$oid":"59fc8401449b71fe7636ed0a"},"actor":{"$oid":"59fc83331fc54c9d4ce0352c"},"post_id":117,"picture":"playing_minecraft.jpg","module":"presentation","likes":3,"lowread":11,"highread":189,"time":180000}
{"_id":{"$oid":"59fc8a70449b71fe76371892"},"actor":{"$oid":"59fc83331fc54c9d4ce034fd"},"reply":{"$oid":"59fc8401449b71fe7636ec9d"},"body":"i can't believe this!!! ugh!!!","module":"presentation","likes":2,"lowread":17,"highread":189,"time":-2340000}
{"_id":{"$oid":"59fc8a70449b71fe76371893"},"actor":{"$oid":"59fc83331fc54c9d4ce034fe"},"reply":{"$oid":"59fc8401449b71fe7636eca3"},"body":"idk it seems kind of sketch...","module":"presentation","likes":5,"lowread":19,"highread":175,"time":-2700000}
{"_id":{"$oid":"59fc8a70449b71fe76371894"},"actor":{"$oid":"59fc83331fc54c9d4ce03544"},"reply":{"$oid":"59fc8401449b71fe7636ecab"},"body":"or maybe they named the bird after the app...?","module":"presentation","likes":3,"lowread":19,"highread":197,"time":2880000}
{"_id":{"$oid":"59fc8a70449b71fe76371895"},"actor":{"$oid":"59fc83331fc54c9d4ce0353f"},"reply":{"$oid":"59fc8401449b71fe7636ecb1"},"body":"Does this mean I don't have to study anymore??","module":"presentation","likes":4,"lowread":16,"highread":151,"time":1080000}
{"_id":{"$oid":"59fc8a70449b71fe76371896"},"actor":{"$oid":"59fc83331fc54c9d4ce03537"},"reply":{"$oid":"59fc8401449b71fe7636ecb7"},"body":"I already eat it every day thoooo","module":"presentation","likes":1,"lowread":18,"highread":145,"time":720000}
{"_id":{"$oid":"59fc8a70449b71fe76371897"},"actor":{"$oid":"59fc83331fc54c9d4ce03531"},"reply":{"$oid":"59fc8401449b71fe7636ecbf"},"body":"ummm what this can't be a thing","module":"presentation","likes":1,"lowread":7,"highread":189,"time":120000}
{"_id":{"$oid":"59fc8a70449b71fe76371898"},"actor":{"$oid":"59fc83331fc54c9d4ce03533"},"reply":{"$oid":"59fc8401449b71fe7636eca1"},"body":"this looks so professional wow","module":"presentation","likes":2,"lowread":18,"highread":162,"time":-3240000}
{"_id":{"$oid":"59fc8a70449b71fe76371899"},"actor":{"$oid":"59fc83331fc54c9d4ce0353d"},"reply":{"$oid":"59fc8401449b71fe7636eca7"},"body":"thats so sad i love exercise","module":"presentation","likes":4,"lowread":16,"highread":158,"time":2700000}
{"_id":{"$oid":"59fc8a70449b71fe7637189a"},"actor":{"$oid":"59fc83331fc54c9d4ce03506"},"reply":{"$oid":"59fc8401449b71fe7636ecae"},"body":"I would totally take a bath with Saturn","module":"presentation","likes":1,"lowread":18,"highread":172,"time":1620000}
{"_id":{"$oid":"59fc8a70449b71fe7637189b"},"actor":{"$oid":"59fc83331fc54c9d4ce03501"},"reply":{"$oid":"59fc8401449b71fe7636ecb4"},"body":"ooooh that's nasty","module":"presentation","likes":5,"lowread":9,"highread":191,"time":1440000}
{"_id":{"$oid":"59fc8a70449b71fe7637189c"},"actor":{"$oid":"59fc83331fc54c9d4ce0350a"},"reply":{"$oid":"59fc8401449b71fe7636ecbb"},"body":"I would leave the country tbh","module":"presentation","likes":1,"lowread":10,"highread":178,"time":540000}
{"_id":{"$oid":"59fc8a70449b71fe7637189d"},"actor":{"$oid":"59fc83331fc54c9d4ce0353c"},"reply":{"$oid":"59fc8401449b71fe7636ec9b"},"body":"This doesn't seem real! The source looks legit though","module":"presentation","likes":6,"lowread":14,"highread":185,"time":-1440000}
{"_id":{"$oid":"59fc8a70449b71fe7637189e"},"actor":{"$oid":"59fc83331fc54c9d4ce034ff"},"reply":{"$oid":"59fc8401449b71fe7636ecc2"},"body":"Sadly they have an ugly sister.","module":"presentation","likes":1,"lowread":10,"highread":149,"time":-1080000}
{"_id":{"$oid":"59fc8a70449b71fe7637189f"},"actor":{"$oid":"59fc83331fc54c9d4ce03514"},"reply":{"$oid":"59fc8401449b71fe7636ecc3"},"body":"Seriously, you should drop out or repeat grade 7 if you can't even deal with such an easy assignment.","module":"presentation","likes":5,"lowread":17,"highread":185,"time":-1800000}
{"_id":{"$oid":"59fc8a70449b71fe763718a0"},"actor":{"$oid":"59fc83331fc54c9d4ce03540"},"reply":{"$oid":"59fc8401449b71fe7636ecc4"},"body":"Lol it's true!! I don't want to see her at school anymore","module":"presentation","likes":1,"lowread":19,"highread":150,"time":-2160000}
{"_id":{"$oid":"59fc8a70449b71fe763718a1"},"actor":{"$oid":"59fc83331fc54c9d4ce0351b"},"reply":{"$oid":"59fc8401449b71fe7636ecc4"},"body":"Wait what are you guys doing?","module":"presentation","likes":2,"lowread":9,"highread":196,"time":-2520000}
{"_id":{"$oid":"59fc8a70449b71fe763718a2"},"actor":{"$oid":"59fc83331fc54c9d4ce03502"},"reply":{"$oid":"59fc8401449b71fe7636ecc5"},"body":"I feel you bro. He's the worst deskmate","module":"presentation","likes":2,"lowread":17,"highread":194,"time":-3240000}
{"_id":{"$oid":"59fc8a70449b71fe763718a3"},"actor":{"$oid":"59fc83331fc54c9d4ce03525"},"reply":{"$oid":"59fc8401449b71fe7636ecc6"},"body":"haha glad that I'm not the only one who think so","module":"presentation","likes":3,"lowread":6,"highread":189,"time":-3540000}
{"_id":{"$oid":"59fc8a70449b71fe763718a4"},"actor":{"$oid":"59fc83331fc54c9d4ce03511"},"reply":{"$oid":"59fc8401449b71fe7636ecc8"},"body":"Church is so lameeeeeeee.","module":"presentation","likes":6,"lowread":11,"highread":156,"time":3240000}
{"_id":{"$oid":"59fc8a70449b71fe763718a5"},"actor":{"$oid":"59fc83331fc54c9d4ce03514"},"reply":{"$oid":"59fc8401449b71fe7636eccf"},"body":"He ruined our group photo 😭","module":"presentation","likes":1,"lowread":15,"highread":149,"time":2880000}
{"_id":{"$oid":"59fc8a70449b71fe763718a6"},"actor":{"$oid":"59fc83331fc54c9d4ce03518"},"reply":{"$oid":"59fc8401449b71fe7636eccf"},"body":"Yes plzzzzzzzz! You are an angel!!!","module":"presentation","likes":3,"lowread":9,"highread":166,"time":1800000}
{"_id":{"$oid":"59fc8a70449b71fe763718a7"},"actor":{"$oid":"59fc83331fc54c9d4ce03511"},"reply":{"$oid":"59fc8401449b71fe7636ecd4"},"body":"No one wants to hang out with you :P","module":"presentation","likes":1,"lowread":10,"highread":184,"time":1260000}
{"_id":{"$oid":"59fc8a70449b71fe763718a8"},"actor":{"$oid":"59fc83331fc54c9d4ce0352b"},"reply":{"$oid":"59fc8401449b71fe7636ecd4"},"body":"Yeah^^ why don't you just go by yourself xD","module":"presentation","likes":2,"lowread":9,"highread":190,"time":900000}
{"_id":{"$oid":"59fc8a70449b71fe763718a9"},"actor":{"$oid":"59fc83331fc54c9d4ce0350b"},"reply":{"$oid":"59fc8401449b71fe7636ecd0"},"body":"No one cares about your lameeee bday","module":"presentation","likes":6,"lowread":18,"highread":190,"time":720000}
{"_id":{"$oid":"59fc8a70449b71fe763718aa"},"actor":{"$oid":"59fc83331fc54c9d4ce03513"},"reply":{"$oid":"59fc8401449b71fe7636ecd3"},"body":"Lol. She's so annoying.","module":"presentation","likes":5,"lowread":17,"highread":188,"time":360000}
{"_id":{"$oid":"59fc8a70449b71fe763718ab"},"actor":{"$oid":"59fc83331fc54c9d4ce03540"},"reply":{"$oid":"59fc8401449b71fe7636eceb"},"body":"jealous!!!!!","module":"presentation","likes":2,"lowread":19,"highread":153,"time":-960000}
{"_id":{"$oid":"59fc8a70449b71fe763718ac"},"actor":{"$oid":"59fc83331fc54c9d4ce0353b"},"reply":{"$oid":"59fc8401449b71fe7636ecee"},"body":"take me with u next time !!!","module":"presentation","likes":1,"lowread":16,"highread":177,"time":-1680000}
{"_id":{"$oid":"59fc8a70449b71fe763718ad"},"actor":{"$oid":"59fc83331fc54c9d4ce03510"},"reply":{"$oid":"59fc8401449b71fe7636ecef"},"body":"ok this is honestly so good","module":"presentation","likes":1,"lowread":9,"highread":164,"time":-1800000}
{"_id":{"$oid":"59fc8a70449b71fe763718ae"},"actor":{"$oid":"59fc83331fc54c9d4ce0353e"},"reply":{"$oid":"59fc8401449b71fe7636ecef"},"body":"woooah that's pretty good","module":"presentation","likes":2,"lowread":7,"highread":168,"time":-2040000}
{"_id":{"$oid":"59fc8a70449b71fe763718af"},"actor":{"$oid":"59fc83331fc54c9d4ce03522"},"reply":{"$oid":"59fc8401449b71fe7636ecf0"},"body":"That seems... unhygenic.","module":"presentation","likes":4,"lowread":19,"highread":157,"time":-1800000}
{"_id":{"$oid":"59fc8a70449b71fe763718b0"},"actor":{"$oid":"59fc83331fc54c9d4ce03506"},"reply":{"$oid":"59fc8401449b71fe7636ecf0"},"body":"huhhhh...?","module":"presentation","likes":6,"lowread":6,"highread":195,"time":-2100000}
{"_id":{"$oid":"59fc8a70449b71fe763718b1"},"actor":{"$oid":"59fc83331fc54c9d4ce03530"},"reply":{"$oid":"59fc8401449b71fe7636ecf0"},"body":"fail lol","module":"presentation","likes":6,"lowread":16,"highread":173,"time":-2640000}
{"_id":{"$oid":"59fc8a70449b71fe763718b2"},"actor":{"$oid":"59fc83331fc54c9d4ce0353a"},"reply":{"$oid":"59fc8401449b71fe7636ecf1"},"body":"cw to dance at tay swift","module":"presentation","likes":1,"lowread":19,"highread":175,"time":-2340000}
{"_id":{"$oid":"59fc8a70449b71fe763718b3"},"actor":{"$oid":"59fc83331fc54c9d4ce03525"},"reply":{"$oid":"59fc8401449b71fe7636ecf6"},"body":"Thanks for the invite :(","module":"presentation","likes":2,"lowread":9,"highread":187,"time":-3300000}
{"_id":{"$oid":"59fc8a70449b71fe763718b4"},"actor":{"$oid":"59fc83331fc54c9d4ce03504"},"reply":{"$oid":"59fc8401449b71fe7636ecfa"},"body":"Looks disgusting...I'd never eat that!!","module":"presentation","likes":1,"lowread":8,"highread":199,"time":3000000}
{"_id":{"$oid":"59fc8a70449b71fe763718b5"},"actor":{"$oid":"59fc83331fc54c9d4ce0353a"},"reply":{"$oid":"59fc8401449b71fe7636ecfa"},"body":"Annie's is my favvvvvvv","module":"presentation","likes":1,"lowread":14,"highread":187,"time":3000000}
{"_id":{"$oid":"59fc8a70449b71fe763718b6"},"actor":{"$oid":"59fc83331fc54c9d4ce03544"},"reply":{"$oid":"59fc8401449b71fe7636ecfd"},"body":"its all fun and games till u step on one of those suckers lol","module":"presentation","likes":2,"lowread":17,"highread":186,"time":2580000}
{"_id":{"$oid":"59fc8a70449b71fe763718b7"},"actor":{"$oid":"59fc83331fc54c9d4ce0352b"},"reply":{"$oid":"59fc8401449b71fe7636ed01"},"body":"update: i ate it in like three bites","module":"presentation","likes":2,"lowread":17,"highread":150,"time":1860000}
{"_id":{"$oid":"59fc8a70449b71fe763718b8"},"actor":{"$oid":"59fc83331fc54c9d4ce0351e"},"reply":{"$oid":"59fc8401449b71fe7636ed01"},"body":"Looks delish!","module":"presentation","likes":1,"lowread":17,"highread":180,"time":1500000}
{"_id":{"$oid":"59fc8a70449b71fe763718b9"},"actor":{"$oid":"59fc83331fc54c9d4ce0353e"},"reply":{"$oid":"59fc8401449b71fe7636ed09"},"body":"Can you name him mr.feathers omg","module":"presentation","likes":1,"lowread":13,"highread":151,"time":-3300000}
